mechanism/__init__.py
mechanism/_player.py
mechanism/appearance.json
mechanism/cams.py
mechanism/dataframe.py
mechanism/gears.py
mechanism/mechanism.py
mechanism/vectors.py
mechanism-1.1.10.dist-info/METADATA
mechanism-1.1.10.dist-info/WHEEL
mechanism-1.1.10.dist-info/top_level.txt
mechanism-1.1.10.dist-info/RECORD
