Metadata-Version: 2.4
Name: mechanism
Version: 1.1.10
Summary: A package that provides a kinematic analysis of mechanisms and cams and custom tooth profile for spur gears.
Home-page: https://github.com/gabemorris12/mechanism
Author: Gabe Morris
Author-email: gabemorris1231@gmail.com
License: MIT
Keywords: mechanism,kinematic,cams,linkages,analysis,animations
Classifier: Development Status :: 5 - Production/Stable
Classifier: License :: OSI Approved :: MIT License
Classifier: Operating System :: Microsoft :: Windows
Classifier: Programming Language :: Python :: 3.10
Requires-Dist: matplotlib
Requires-Dist: scipy
Provides-Extra: notebook
Requires-Dist: ipympl; extra == "notebook"
Requires-Dist: notebook; extra == "notebook"
Dynamic: author
Dynamic: author-email
Dynamic: classifier
Dynamic: description
Dynamic: description-content-type
Dynamic: home-page
Dynamic: keywords
Dynamic: license
Dynamic: provides-extra
Dynamic: requires-dist
Dynamic: summary
